[
    {
        "id": "1",
        "status": "1",
        "voltage": "345.600",
        "current": "123.400",
        "power": "456.700",
        "reg_time": "2018-09-20 21:09:27"
    },
    {
        "id": "2",
        "status": "1",
        "voltage": "12.000",
        "current": "12.000",
        "power": "34.000",
        "reg_time": "2018-09-20 21:41:24"
    },
    {
        "id": "3",
        "status": "1",
        "voltage": "12.000",
        "current": "12.000",
        "power": "34.000",
        "reg_time": "2018-09-20 22:00:20"
    },
    {
        "id": "4",
        "status": "1",
        "voltage": "2.000",
        "current": "2.000",
        "power": "1.000",
        "reg_time": "2018-09-20 22:21:53"
    }
]